{
  "contacts": [
    {
      "contact": {
        "id": "1",
        "fullName": "Emad Hereba 5",
        "email": "tuguiaegipcio@gmail.com",
        "confirmationType": "phone",
        "gender": "male"
      },
      "id": 1
    },
    {
      "contact": {
        "id": "2",
        "fullName": "Emad Radwan",
        "email": "eradawam1967@gmail.com",
        "confirmationType": "email",
        "gender": "male"
      },
      "id": 2
    },
    {
      "contact": {
        "id": "3",
        "fullName": "Yahia Emad Hereba",
        "email": "yahiahereba@gmail.com",
        "confirmationType": "phone",
        "gender": "male"
      },
      "id": 3
    },
    {
      "contact": {
        "id": "4",
        "fullName": "Ahmed Emad Hereba",
        "email": "ahmedhereba@gmail.com",
        "confirmationType": "email",
        "gender": "male"
      },
      "id": 4
    },
    {
      "contact": {
        "id": "5",
        "fullName": "Senora Costa Rica",
        "email": "costarica@gmail.com",
        "confirmationType": "email",
        "gender": "female"
      },
      "id": 5
    }
  ]
}